{
    "key": "group_669faa53b11e1",
    "title": "Meta - Property",
    "fields": [
        {
            "key": "field_669fac1b9ef00",
            "label": "Property",
            "name": "",
            "aria-label": "",
            "type": "tab",
            "instructions": "",
            "required": 0,
            "conditional_logic": 0,
            "wrapper": {
                "width": "",
                "class": "",
                "id": ""
            },
            "placement": "left",
            "endpoint": 0,
            "selected": 0
        },
        {
            "key": "field_669faa5430718",
            "label": "Listing Status",
            "name": "listing_status",
            "aria-label": "",
            "type": "select",
            "instructions": "",
            "required": 0,
            "conditional_logic": 0,
            "wrapper": {
                "width": "50",
                "class": "",
                "id": ""
            },
            "choices": {
                "for-sale": "For Sale",
                "pending": "Pending"
            },
            "default_value": false,
            "return_format": "value",
            "multiple": 0,
            "allow_null": 0,
            "ui": 0,
            "ajax": 0,
            "placeholder": ""
        },
        {
            "key": "field_669faa7d30719",
            "label": "Price",
            "name": "price",
            "aria-label": "",
            "type": "number",
            "instructions": "",
            "required": 0,
            "conditional_logic": 0,
            "wrapper": {
                "width": "50",
                "class": "",
                "id": ""
            },
            "default_value": "",
            "min": "",
            "max": "",
            "placeholder": "",
            "step": "",
            "prepend": "$",
            "append": ""
        },
        {
            "key": "field_669faa953071a",
            "label": "Number of Bedrooms",
            "name": "number_of_bedrooms",
            "aria-label": "",
            "type": "number",
            "instructions": "",
            "required": 0,
            "conditional_logic": 0,
            "wrapper": {
                "width": "33",
                "class": "",
                "id": ""
            },
            "default_value": "",
            "min": "",
            "max": "",
            "placeholder": "",
            "step": "",
            "prepend": "",
            "append": ""
        },
        {
            "key": "field_669faa9e3071b",
            "label": "Number of Bathrooms",
            "name": "number_of_bathrooms",
            "aria-label": "",
            "type": "number",
            "instructions": "",
            "required": 0,
            "conditional_logic": 0,
            "wrapper": {
                "width": "33",
                "class": "",
                "id": ""
            },
            "default_value": "",
            "min": "",
            "max": "",
            "placeholder": "",
            "step": "",
            "prepend": "",
            "append": ""
        },
        {
            "key": "field_669faaa83071c",
            "label": "Square Footage",
            "name": "square_footage",
            "aria-label": "",
            "type": "number",
            "instructions": "",
            "required": 0,
            "conditional_logic": 0,
            "wrapper": {
                "width": "33",
                "class": "",
                "id": ""
            },
            "default_value": "",
            "min": "",
            "max": "",
            "placeholder": "",
            "step": "",
            "prepend": "",
            "append": ""
        },
        {
            "key": "field_669faadd3071e",
            "label": "Property Address",
            "name": "property_address",
            "aria-label": "",
            "type": "google_map",
            "instructions": "",
            "required": 0,
            "conditional_logic": 0,
            "wrapper": {
                "width": "",
                "class": "",
                "id": ""
            },
            "center_lat": "",
            "center_lng": "",
            "zoom": "",
            "height": ""
        },
        {
            "key": "field_669fac299ef01",
            "label": "Agent",
            "name": "",
            "aria-label": "",
            "type": "tab",
            "instructions": "",
            "required": 0,
            "conditional_logic": 0,
            "wrapper": {
                "width": "",
                "class": "",
                "id": ""
            },
            "placement": "left",
            "endpoint": 0,
            "selected": 0
        },
        {
            "key": "field_669fab1d3071f",
            "label": "Agent Name",
            "name": "agent_name",
            "aria-label": "",
            "type": "text",
            "instructions": "",
            "required": 0,
            "conditional_logic": 0,
            "wrapper": {
                "width": "50",
                "class": "",
                "id": ""
            },
            "default_value": "",
            "maxlength": "",
            "placeholder": "",
            "prepend": "",
            "append": ""
        },
        {
            "key": "field_669fab2f30720",
            "label": "Agent Phone",
            "name": "agent_phone",
            "aria-label": "",
            "type": "text",
            "instructions": "",
            "required": 0,
            "conditional_logic": 0,
            "wrapper": {
                "width": "50",
                "class": "",
                "id": ""
            },
            "default_value": "",
            "maxlength": "",
            "placeholder": "",
            "prepend": "",
            "append": ""
        },
        {
            "key": "field_669fab3630721",
            "label": "Agent Email",
            "name": "agent_email",
            "aria-label": "",
            "type": "text",
            "instructions": "",
            "required": 0,
            "conditional_logic": 0,
            "wrapper": {
                "width": "50",
                "class": "",
                "id": ""
            },
            "default_value": "",
            "maxlength": "",
            "placeholder": "",
            "prepend": "",
            "append": ""
        },
        {
            "key": "field_669fab4830722",
            "label": "Compensation Percentage",
            "name": "compensation_percentage",
            "aria-label": "",
            "type": "number",
            "instructions": "",
            "required": 0,
            "conditional_logic": 0,
            "wrapper": {
                "width": "50",
                "class": "",
                "id": ""
            },
            "default_value": "",
            "min": "",
            "max": "",
            "placeholder": "",
            "step": "",
            "prepend": "",
            "append": "%"
        }
    ],
    "location": [
        [
            {
                "param": "post_type",
                "operator": "==",
                "value": "property"
            }
        ]
    ],
    "menu_order": 0,
    "position": "normal",
    "style": "default",
    "label_placement": "top",
    "instruction_placement": "label",
    "hide_on_screen": "",
    "active": true,
    "description": "",
    "show_in_rest": 0,
    "modified": 1721746350
}
